tradenity_django/__init__.py
tradenity_django/sdk/__init__.py
tradenity_django/sdk/ext/__init__.py
tradenity_django/sdk/ext/auth.py
tradenity_django/sdk/ext/middleware/__init__.py
tradenity_django/sdk/ext/middleware/current_request.py
tradenity_django/sdk/ext/middleware/session_expiry_handler.py
tradenity_django_ext-0.7.0.dist-info/AUTHORS.rst
tradenity_django_ext-0.7.0.dist-info/LICENSE
tradenity_django_ext-0.7.0.dist-info/METADATA
tradenity_django_ext-0.7.0.dist-info/WHEEL
tradenity_django_ext-0.7.0.dist-info/entry_points.txt
tradenity_django_ext-0.7.0.dist-info/top_level.txt
tradenity_django_ext-0.7.0.dist-info/RECORD
