Metadata-Version: 2.1
Name: tradenity-django-ext
Version: 0.7.0
Summary: Django extensions for Tradenity Python SDK
Home-page: https://github.com/tradenity/python-sdk-django-ext
Author: Joseph Fouad
Author-email: tradenity@tradenity.com
License: APACHE
Platform: UNKNOWN
Classifier: Development Status :: 5 - Production/Stable
Classifier: Intended Audience :: Developers
Classifier: License :: OSI Approved :: Apache Software License
Classifier: Natural Language :: English
Classifier: Programming Language :: Python :: 2
Classifier: Programming Language :: Python :: 2.7
Requires-Dist: tradenity
